accern_xyme/__init__.py
accern_xyme/__main__.py
accern_xyme/accern_xyme.py
accern_xyme/py.typed
accern_xyme/types.py
accern_xyme/util.py
accern_xyme/v2/__init__.py
accern_xyme/v2/legacy.py
accern_xyme/v2/util.py
accern_xyme/v3/__init__.py
accern_xyme/v3/accern_xyme.py
accern_xyme/v3/types.py
accern_xyme/v3/util.py
accern_xyme-4.2.1.dist-info/LICENSE
accern_xyme-4.2.1.dist-info/METADATA
accern_xyme-4.2.1.dist-info/WHEEL
accern_xyme-4.2.1.dist-info/top_level.txt
accern_xyme-4.2.1.dist-info/RECORD
