Metadata-Version: 2.1
Name: accern-xyme
Version: 4.2.1
Summary: AccernXYME is a library for easily accessing XYME via python.
Home-page: https://github.com/Accern/accern-xyme
Author: Accern Corp.
Author-email: josua.krause@accern.com
License: MIT
Keywords: XYME AI machine learning client
Classifier: Development Status :: 4 - Beta
Classifier: License :: OSI Approved :: MIT License
Classifier: Operating System :: OS Independent
Classifier: Programming Language :: Python :: 3.6
Classifier: Programming Language :: Python :: 3.7
Classifier: Programming Language :: Python :: 3.8
Classifier: Programming Language :: Python :: 3.9
Classifier: Programming Language :: Python :: 3
Requires-Python: >=3.6
License-File: LICENSE
Requires-Dist: graphviz (>=0.14.1)
Requires-Dist: numpy (>=1.17.3)
Requires-Dist: pandas (>=0.25.3)
Requires-Dist: pyarrow (>=2.0.0)
Requires-Dist: quick-server (>=0.7.14)
Requires-Dist: requests (>=2.22.0)
Requires-Dist: RestrictedPython (>=5.0)
Requires-Dist: scipy (>=1.4.1)
Requires-Dist: torch (>=1.5.1)
Requires-Dist: typing-extensions (>=3.7.4.1)
